[
  {
    "traditional": "西瓜",
    "simplified": "西瓜",
    "pinyin": "xī guā",
    "english": "Watermelon"
  },
  {
    "traditional": "平",
    "simplified": "平",
    "pinyin": "píng",
    "english": "Level"
  },
  {
    "traditional": "芒果",
    "simplified": "芒果",
    "pinyin": "máng guǒ",
    "english": "Mango"
  },
  {
    "traditional": "香蕉",
    "simplified": "香蕉",
    "pinyin": "xiāng jiāo",
    "english": "Banana"
  },
  {
    "traditional": "藍莓",
    "simplified": "蓝莓",
    "pinyin": "lán méi",
    "english": "Blueberry"
  }
]
